dynamixel_api/__init__.py
dynamixel_api/custom_protocol2_packet_handler.py
dynamixel_api/dynamixel_connector.py
dynamixel_api/motor_control.py
dynamixel_api/sweep.py
dynamixel_api/models/__init__.py
dynamixel_api/models/rhp12rn.py
dynamixel_api/models/rhp12rna.py
dynamixel_api/models/xl430w250t.py
dynamixel_api-1.0.3.dist-info/licenses/LICENSE
dynamixel_api-1.0.3.dist-info/METADATA
dynamixel_api-1.0.3.dist-info/WHEEL
dynamixel_api-1.0.3.dist-info/entry_points.txt
dynamixel_api-1.0.3.dist-info/top_level.txt
dynamixel_api-1.0.3.dist-info/RECORD
