Metadata-Version: 2.4
Name: dynamixel-api
Version: 1.0.3
Summary: Python controller for grippers powered by DYNAMIXEL motors.
Author-email: Tim Schneider <tim@robot-learning.de>, Erik Helmut <erik.helmut1@gmail.com>
Project-URL: Homepage, https://github.com/TimSchneider42/dynamixel-api
Project-URL: Issues, https://github.com/TimSchneider42/dynamixel-api/issues
Classifier: Programming Language :: Python :: 3
Classifier: License :: OSI Approved :: MIT License
Classifier: Operating System :: POSIX :: Linux
Requires-Python: >=3.8
License-File: LICENSE
Requires-Dist: dynamixel-sdk
Requires-Dist: pyserial>=3.5
Dynamic: license-file
